README.md
setup.py
Taara.egg-info/PKG-INFO
Taara.egg-info/SOURCES.txt
Taara.egg-info/dependency_links.txt
Taara.egg-info/entry_points.txt
Taara.egg-info/top_level.txt
lib/retrace.jar
lib/retrace.sh
taara/__init__.py
taara/anr_chain.py
taara/anr_file.py
taara/anr_guess.py
taara/anr_re.py
taara/anr_state.py
taara/memory_info.py
taara/retrace.py
taara/taara_error.py
taara/taara_teminal_color.py
taara/taara_utils.py
taara/stack/__init__.py
taara/stack/anr_binder.py
taara/stack/anr_lock.py
taara/stack/anr_stack.py